[
  {
    "key": "sol_failcut",
    "thesis": "Keep SOL entry logic, but cut SOL earlier when momentum fails immediately after entry.",
    "endEquity": 806660.65,
    "cagrPct": 299.25,
    "maxDrawdownPct": -36.78,
    "profitFactor": 2.16,
    "tradeCount": 94,
    "solTradeCount": 23,
    "solLossCount": 13,
    "solWinCount": 10,
    "solPnl": -59150.85,
    "topSolLossReason": "symbol-weak-exit",
    "topSolLossReasonCount": 9
  },
  {
    "key": "sol_score_minus10",
    "thesis": "Lower SOL rank slightly more so it needs to be more clearly superior before selection.",
    "endEquity": 786438.12,
    "cagrPct": 296.07,
    "maxDrawdownPct": -37.15,
    "profitFactor": 2.109,
    "tradeCount": 93,
    "solTradeCount": 18,
    "solLossCount": 10,
    "solWinCount": 8,
    "solPnl": -35479.23,
    "topSolLossReason": "sma-break",
    "topSolLossReasonCount": 5
  },
  {
    "key": "sol_score_minus10_plus_failcut",
    "thesis": "Combine stronger SOL demotion with early failure cut.",
    "endEquity": 767043.85,
    "cagrPct": 292.96,
    "maxDrawdownPct": -41.17,
    "profitFactor": 2.143,
    "tradeCount": 93,
    "solTradeCount": 21,
    "solLossCount": 11,
    "solWinCount": 10,
    "solPnl": -54616.38,
    "topSolLossReason": "symbol-weak-exit",
    "topSolLossReasonCount": 8
  },
  {
    "key": "base_v4",
    "thesis": "Current production v4.",
    "endEquity": 744852.64,
    "cagrPct": 289.34,
    "maxDrawdownPct": -38.41,
    "profitFactor": 2.101,
    "tradeCount": 94,
    "solTradeCount": 20,
    "solLossCount": 12,
    "solWinCount": 8,
    "solPnl": -43722.34,
    "topSolLossReason": "sma-break",
    "topSolLossReasonCount": 6
  },
  {
    "key": "sol_score_minus12",
    "thesis": "Lower SOL rank further to cut marginal SOL entries.",
    "endEquity": 722321.06,
    "cagrPct": 285.59,
    "maxDrawdownPct": -37.15,
    "profitFactor": 2.072,
    "tradeCount": 96,
    "solTradeCount": 18,
    "solLossCount": 10,
    "solWinCount": 8,
    "solPnl": -45675.7,
    "topSolLossReason": "sma-break",
    "topSolLossReasonCount": 4
  },
  {
    "key": "sol_loose_breakout_plus_demote",
    "thesis": "Require SOL to break out a bit more cleanly while still demoting ranking modestly.",
    "endEquity": 172271.55,
    "cagrPct": 145.37,
    "maxDrawdownPct": -38.19,
    "profitFactor": 1.919,
    "tradeCount": 86,
    "solTradeCount": 3,
    "solLossCount": 2,
    "solWinCount": 1,
    "solPnl": -173.37,
    "topSolLossReason": "strict-extra-rotate",
    "topSolLossReasonCount": 1
  },
  {
    "key": "sol_quality_gate",
    "thesis": "Keep SOL in the universe, but require better volume and momentum quality before taking it.",
    "endEquity": 143750.05,
    "cagrPct": 131.76,
    "maxDrawdownPct": -40.89,
    "profitFactor": 1.809,
    "tradeCount": 86,
    "solTradeCount": 2,
    "solLossCount": 2,
    "solWinCount": 0,
    "solPnl": -1901.22,
    "topSolLossReason": "strict-extra-rotate",
    "topSolLossReasonCount": 1
  },
  {
    "key": "sol_quality_gate_strict",
    "thesis": "Require clearly stronger SOL participation before entry, aiming to remove marginal losers.",
    "endEquity": 143750.05,
    "cagrPct": 131.76,
    "maxDrawdownPct": -40.89,
    "profitFactor": 1.809,
    "tradeCount": 86,
    "solTradeCount": 2,
    "solLossCount": 2,
    "solWinCount": 0,
    "solPnl": -1901.22,
    "topSolLossReason": "strict-extra-rotate",
    "topSolLossReasonCount": 1
  }
]