[
  {
    "key": "base_v6",
    "thesis": "Current production v6.",
    "endEquity": 981154.22,
    "cagrPct": 324.68,
    "maxDrawdownPct": -38.41,
    "profitFactor": 2.109,
    "winRatePct": 53.68,
    "tradeCount": 95,
    "exposurePct": 39.66,
    "solTradeCount": 18,
    "solWins": 7,
    "solLosses": 11,
    "solNetPnl": -63433.96
  },
  {
    "key": "sol_5pct_only",
    "thesis": "SOL only 5% allocation, no extra filter.",
    "endEquity": 851790.12,
    "cagrPct": 306.16,
    "maxDrawdownPct": -31.66,
    "profitFactor": 2.372,
    "winRatePct": 53.68,
    "tradeCount": 95,
    "exposurePct": 39.66,
    "solTradeCount": 18,
    "solWins": 7,
    "solLosses": 11,
    "solNetPnl": -2193.93
  },
  {
    "key": "sol_5pct_eff_vol",
    "thesis": "SOL 5% allocation + require stronger efficiency and volume.",
    "endEquity": 745624.01,
    "cagrPct": 289.47,
    "maxDrawdownPct": -35.29,
    "profitFactor": 2.152,
    "winRatePct": 53.76,
    "tradeCount": 93,
    "exposurePct": 38.84,
    "solTradeCount": 14,
    "solWins": 6,
    "solLosses": 8,
    "solNetPnl": 892.48
  },
  {
    "key": "sol_100pct_eff_vol",
    "thesis": "SOL 100% allocation + require stronger efficiency and volume.",
    "endEquity": 743159.37,
    "cagrPct": 289.06,
    "maxDrawdownPct": -38.41,
    "profitFactor": 2.097,
    "winRatePct": 53.76,
    "tradeCount": 93,
    "exposurePct": 38.84,
    "solTradeCount": 14,
    "solWins": 6,
    "solLosses": 8,
    "solNetPnl": 12040.76
  },
  {
    "key": "sol_5pct_eff_vol_accel",
    "thesis": "SOL 5% allocation + stronger efficiency, volume, and momentum acceleration.",
    "endEquity": 469590.21,
    "cagrPct": 236.63,
    "maxDrawdownPct": -37.38,
    "profitFactor": 2.062,
    "winRatePct": 49.44,
    "tradeCount": 89,
    "exposurePct": 37.2,
    "solTradeCount": 7,
    "solWins": 2,
    "solLosses": 5,
    "solNetPnl": -139.82
  },
  {
    "key": "sol_5pct_light_breakout",
    "thesis": "SOL 5% allocation + light breakout gate and stricter quality.",
    "endEquity": 350184.53,
    "cagrPct": 206.88,
    "maxDrawdownPct": -38.08,
    "profitFactor": 1.973,
    "winRatePct": 48.31,
    "tradeCount": 89,
    "exposurePct": 36.64,
    "solTradeCount": 4,
    "solWins": 1,
    "solLosses": 3,
    "solNetPnl": -321.3
  }
]